[
  {
    "name":"Baltimore City Correctional Center",
    "state":"Maryland",
    "agency":"Maryland Department of Public Safety and Correctional Services (DPSCS)",
    "detail_url":"https:\/\/www.dpscs.state.md.us\/locations\/bccc.shtml",
    "facility_type":"Correctional Center",
    "street_address":"901 Greenmount Avenue",
    "city":"Baltimore",
    "zip_code":"21202",
    "phone":"(410) 332-4340",
    "fax":"(410) 576-9470",
    "warden":"Michelle Mann",
    "assistant_warden":"Damilare Adisa - Thomas",
    "facility_administrator":"Vera Wright",
    "security_level":"Minimum, Pre-Release and Work Release",
    "year_opened":1984.0,
    "latitude":39.3002964,
    "longitude":-76.6065375
  },
  {
    "name":"Central Maryland Correctional Facility",
    "state":"Maryland",
    "agency":"Maryland Department of Public Safety and Correctional Services (DPSCS)",
    "detail_url":"https:\/\/www.dpscs.state.md.us\/locations\/cmcf.shtml",
    "facility_type":"Correctional Facility",
    "street_address":"7301 Buttercup Road",
    "city":"Sykesville",
    "zip_code":"21784",
    "phone":"(410) 781-4444",
    "fax":"(410) 781-4414",
    "warden":"Michelle Mann",
    "assistant_warden":"Damilare Adisa-Thomas",
    "facility_administrator":"Genieve Goodall",
    "security_level":"s:",
    "year_opened":1960.0,
    "latitude":39.3723253,
    "longitude":-76.9566545
  },
  {
    "name":"Dorsey Run Correctional Facility",
    "state":"Maryland",
    "agency":"Maryland Department of Public Safety and Correctional Services (DPSCS)",
    "detail_url":"https:\/\/www.dpscs.state.md.us\/locations\/drc.shtml",
    "facility_type":"Correctional Facility",
    "street_address":"2020 Toulson RoadJessup, MD 20794",
    "city":null,
    "zip_code":null,
    "phone":"(410) 379-6020",
    "fax":"(410) 379-6078",
    "warden":"Michelle Mann",
    "assistant_warden":"Damilare Adisa - Thomas",
    "facility_administrator":null,
    "security_level":"s:",
    "year_opened":2013.0,
    "latitude":null,
    "longitude":null
  },
  {
    "name":"Eastern Correctional Institution",
    "state":"Maryland",
    "agency":"Maryland Department of Public Safety and Correctional Services (DPSCS)",
    "detail_url":"https:\/\/www.dpscs.state.md.us\/locations\/eci.shtml",
    "facility_type":"Correctional Institution",
    "street_address":"30420 Revells Neck Road",
    "city":"Westover",
    "zip_code":"21890",
    "phone":"(410) 845-4000",
    "fax":"(410) 651-9585",
    "warden":"William Bailey",
    "assistant_warden":"1",
    "facility_administrator":"Matthew Mitchell",
    "security_level":"s",
    "year_opened":1987.0,
    "latitude":38.1537006,
    "longitude":-75.6965628
  },
  {
    "name":"Jessup Correctional Institution",
    "state":"Maryland",
    "agency":"Maryland Department of Public Safety and Correctional Services (DPSCS)",
    "detail_url":"https:\/\/www.dpscs.state.md.us\/locations\/jci.shtml",
    "facility_type":"Correctional Institution",
    "street_address":null,
    "city":null,
    "zip_code":null,
    "phone":null,
    "fax":"(410) 799-1025",
    "warden":"Damean Stewart",
    "assistant_warden":"Carlos Bivens",
    "facility_administrator":null,
    "security_level":"s",
    "year_opened":1991.0,
    "latitude":null,
    "longitude":null
  },
  {
    "name":"Maryland Correctional Institution - Hagerstown",
    "state":"Maryland",
    "agency":"Maryland Department of Public Safety and Correctional Services (DPSCS)",
    "detail_url":"https:\/\/www.dpscs.state.md.us\/locations\/mcih.shtml",
    "facility_type":"Correctional Institution",
    "street_address":"18601 Roxbury Road",
    "city":"Hagerstown",
    "zip_code":"21746",
    "phone":"(240) 420-1000",
    "fax":null,
    "warden":"Gregory A. Werner",
    "assistant_warden":"Jim Sprecher",
    "facility_administrator":null,
    "security_level":"Medium",
    "year_opened":1932.0,
    "latitude":39.5607829,
    "longitude":-77.7238753
  },
  {
    "name":"Maryland Correctional Institution - Jessup",
    "state":"Maryland",
    "agency":"Maryland Department of Public Safety and Correctional Services (DPSCS)",
    "detail_url":"https:\/\/www.dpscs.state.md.us\/locations\/mcij.shtml",
    "facility_type":"Correctional Institution",
    "street_address":null,
    "city":null,
    "zip_code":null,
    "phone":"(410) 799-7610",
    "fax":"(410) 799-7527",
    "warden":"Geneva Holland",
    "assistant_warden":"Vacant",
    "facility_administrator":null,
    "security_level":"s:",
    "year_opened":1981.0,
    "latitude":null,
    "longitude":null
  },
  {
    "name":"Maryland Correctional Institution - Women",
    "state":"Maryland",
    "agency":"Maryland Department of Public Safety and Correctional Services (DPSCS)",
    "detail_url":"https:\/\/www.dpscs.state.md.us\/locations\/mciw.shtml",
    "facility_type":"Correctional Institution",
    "street_address":null,
    "city":null,
    "zip_code":null,
    "phone":null,
    "fax":"(410) 799-6146",
    "warden":"Tikaya Parker",
    "assistant_warden":"Lorelei Sattler",
    "facility_administrator":null,
    "security_level":"s:",
    "year_opened":null,
    "latitude":null,
    "longitude":null
  },
  {
    "name":"Maryland Correctional Training Center",
    "state":"Maryland",
    "agency":"Maryland Department of Public Safety and Correctional Services (DPSCS)",
    "detail_url":"https:\/\/www.dpscs.state.md.us\/locations\/mctc.shtml",
    "facility_type":"Training Center",
    "street_address":"18800 Roxbury Road",
    "city":"Hagerstown",
    "zip_code":"21746",
    "phone":"(240) 420-1601",
    "fax":"(301) 797-8574",
    "warden":"Cleveland Friday",
    "assistant_warden":"James Wilson",
    "facility_administrator":"- (HED\/EHU):",
    "security_level":"s:",
    "year_opened":1966.0,
    "latitude":39.5647775,
    "longitude":-77.7158347
  },
  {
    "name":"North Branch Correctional Institution",
    "state":"Maryland",
    "agency":"Maryland Department of Public Safety and Correctional Services (DPSCS)",
    "detail_url":"https:\/\/www.dpscs.state.md.us\/locations\/nbci.shtml",
    "facility_type":"Correctional Institution",
    "street_address":"14100 McMullen Highway, S.W.",
    "city":"Cumberland",
    "zip_code":"21502",
    "phone":"(301) 729-7400",
    "fax":"(301) 729-1259",
    "warden":"Keith Arnold",
    "assistant_warden":"Jason Harbaugh",
    "facility_administrator":null,
    "security_level":"s:",
    "year_opened":2003.0,
    "latitude":39.6030841,
    "longitude":-78.8193413
  },
  {
    "name":"Patuxent Institution",
    "state":"Maryland",
    "agency":"Maryland Department of Public Safety and Correctional Services (DPSCS)",
    "detail_url":"https:\/\/www.dpscs.state.md.us\/locations\/pat.shtml",
    "facility_type":"Institution",
    "street_address":"7555 Waterloo Road",
    "city":"Jessup",
    "zip_code":"20794",
    "phone":"(410) 799-3400",
    "fax":"(410) 799-3397",
    "warden":"Paige C. Jones",
    "assistant_warden":"Adeola Obaika, MBA",
    "facility_administrator":null,
    "security_level":"s:",
    "year_opened":null,
    "latitude":39.1646513,
    "longitude":-76.779096
  },
  {
    "name":"Roxbury Correctional Institution",
    "state":"Maryland",
    "agency":"Maryland Department of Public Safety and Correctional Services (DPSCS)",
    "detail_url":"https:\/\/www.dpscs.state.md.us\/locations\/rci.shtml",
    "facility_type":"Correctional Institution",
    "street_address":"18701 Roxbury Road",
    "city":"Hagerstown",
    "zip_code":"21746",
    "phone":"(240) 420-3000",
    "fax":"(410) 415-2126",
    "warden":"Laura Golliday",
    "assistant_warden":"Kate Gorsuch",
    "facility_administrator":null,
    "security_level":"s:",
    "year_opened":1983.0,
    "latitude":39.557484,
    "longitude":-77.7149098
  },
  {
    "name":"Western Correctional Institution",
    "state":"Maryland",
    "agency":"Maryland Department of Public Safety and Correctional Services (DPSCS)",
    "detail_url":"https:\/\/www.dpscs.state.md.us\/locations\/wci.shtml",
    "facility_type":"Correctional Institution",
    "street_address":"13800 McMullen Highway, S.W.",
    "city":"Cumberland",
    "zip_code":"21502",
    "phone":"(301) 729-7000",
    "fax":"(301) 729-7024",
    "warden":"Bethany Cornachia",
    "assistant_warden":"Bradley Butler",
    "facility_administrator":null,
    "security_level":"s",
    "year_opened":1996.0,
    "latitude":39.6057642,
    "longitude":-78.8179145
  }
]